{
  "DOGS/USDT": {
    "direction": "SHORT",
    "confidence": 0.75,
    "count": 2,
    "exchange": "bitget",
    "price": 2.85e-05,
    "last_seen": "2026-02-19T04:11:37.024510+00:00"
  },
  "BONK/USDT": {
    "direction": "SHORT",
    "confidence": 0.75,
    "count": 1,
    "exchange": "gateio",
    "price": 6.257e-06,
    "last_seen": "2026-02-19T04:11:37.024510+00:00"
  },
  "PEOPLE/USDT": {
    "direction": "SHORT",
    "confidence": 0.75,
    "count": 1,
    "exchange": "mexc",
    "price": 0.006821,
    "last_seen": "2026-02-19T04:11:37.024510+00:00"
  },
  "1000BONK/USDT": {
    "direction": "SHORT",
    "confidence": 0.75,
    "count": 1,
    "exchange": "mexc",
    "price": 0.006255,
    "last_seen": "2026-02-19T04:11:37.024510+00:00"
  },
  "MEW/USDT": {
    "direction": "SHORT",
    "confidence": 0.75,
    "count": 1,
    "exchange": "mexc",
    "price": 0.0006071,
    "last_seen": "2026-02-19T04:11:37.024510+00:00"
  },
  "ACT/USDT": {
    "direction": "SHORT",
    "confidence": 0.75,
    "count": 1,
    "exchange": "gateio",
    "price": 0.01467,
    "last_seen": "2026-02-19T04:11:37.024510+00:00"
  }
}