{
  "MUBARAK/USDT": {
    "direction": "SHORT",
    "confidence": 0.75,
    "count": 2,
    "exchange": "gateio",
    "price": 0.01995,
    "last_seen": "2025-11-02T23:11:27.862086+00:00"
  },
  "CHILLGUY/USDT": {
    "direction": "SHORT",
    "confidence": 0.75,
    "count": 1,
    "exchange": "gateio",
    "price": 0.02703,
    "last_seen": "2025-11-02T23:11:27.862086+00:00"
  },
  "PENGU/USDT": {
    "direction": "SHORT",
    "confidence": 0.75,
    "count": 1,
    "exchange": "gateio",
    "price": 0.01761,
    "last_seen": "2025-11-02T23:11:27.862086+00:00"
  },
  "SPX/USDT": {
    "direction": "SHORT",
    "confidence": 0.75,
    "count": 1,
    "exchange": "bitget",
    "price": 0.8721,
    "last_seen": "2025-11-02T23:11:27.862086+00:00"
  },
  "MOODENG/USDT": {
    "direction": "SHORT",
    "confidence": 0.75,
    "count": 1,
    "exchange": "okx",
    "price": 0.10375,
    "last_seen": "2025-11-02T23:11:27.862086+00:00"
  }
}